Metadata-Version: 2.1
Name: doc2term
Version: 0.1
Summary: A fast NLP tokenizer that detects tokens and remove duplications and punctuations
Home-page: https://github.com/callforpapers-source/doc2term
Maintainer: Saeed Dehqan
Maintainer-email: saeed.dehghan@owasp.org
License: Apache License, Version 2.0
Keywords: tokenizer,NLP,punctuation,standarization,duplicate-detection,text-processing,text-tokenizing,doc2term
Platform: UNKNOWN
Classifier: License :: OSI Approved :: Apache Software License
Classifier: Programming Language :: Python :: 3.7
Classifier: Programming Language :: Python :: 3.8
Classifier: Programming Language :: Python :: 3.9
Requires-Python: >=3.7
